codenrock/__init__.py
codenrock/cli.py
codenrock/config.json
codenrock-0.94.dist-info/METADATA
codenrock-0.94.dist-info/WHEEL
codenrock-0.94.dist-info/entry_points.txt
codenrock-0.94.dist-info/top_level.txt
codenrock-0.94.dist-info/RECORD
