Metadata-Version: 2.1
Name: codenrock
Version: 0.94
Requires-Dist: requests
Requires-Dist: tuspy
Requires-Dist: argparse
Requires-Dist: tqdm
Requires-Dist: zipfile
